spox/__init__.py
spox/_adapt.py
spox/_attributes.py
spox/_build.py
spox/_debug.py
spox/_exceptions.py
spox/_fields.py
spox/_function.py
spox/_future.py
spox/_graph.py
spox/_inline.py
spox/_internal_op.py
spox/_node.py
spox/_public.py
spox/_schemas.py
spox/_scope.py
spox/_shape.py
spox/_standard.py
spox/_traverse.py
spox/_type_inference_utils.py
spox/_type_system.py
spox/_utils.py
spox/_value_prop.py
spox/_var.py
spox/py.typed
spox/opset/ai/onnx/v17.py
spox/opset/ai/onnx/v18.py
spox/opset/ai/onnx/v19.py
spox/opset/ai/onnx/v20.py
spox/opset/ai/onnx/v21.py
spox/opset/ai/onnx/v22.py
spox/opset/ai/onnx/v23.py
spox/opset/ai/onnx/v24.py
spox/opset/ai/onnx/ml/v3.py
spox/opset/ai/onnx/ml/v4.py
spox/opset/ai/onnx/ml/v5.py
spox-0.17.0.dist-info/licenses/LICENSE
spox-0.17.0.dist-info/METADATA
spox-0.17.0.dist-info/WHEEL
spox-0.17.0.dist-info/top_level.txt
spox-0.17.0.dist-info/RECORD
