Metadata-Version: 2.4
Name: spox
Version: 0.17.0
Summary: A framework for constructing ONNX computational graphs.
Author-email: Jakub Bachurski <kbachurski@gmail.com>, Christian Bourjau <christian.bourjau@quantco.com>
Maintainer-email: Jakub Bachurski <kbachurski@gmail.com>, Christian Bourjau <christian.bourjau@quantco.com>
Project-URL: Source, https://github.com/quantco/spox
Keywords: machine-learning,onnx
Classifier: Development Status :: 5 - Production/Stable
Classifier: License :: OSI Approved :: BSD License
Classifier: Operating System :: OS Independent
Classifier: Programming Language :: Python :: 3
Classifier: Programming Language :: Python :: 3.10
Classifier: Programming Language :: Python :: 3.11
Classifier: Programming Language :: Python :: 3.12
Classifier: Programming Language :: Python :: 3.13
Classifier: Programming Language :: Python :: 3.14
Requires-Python: >=3.10
License-File: LICENSE
Requires-Dist: numpy
Requires-Dist: onnx>=1.13
Requires-Dist: packaging
Dynamic: license-file
